rv32i/iiitb_rv32i.v
module iiitb_rv32i(clk,RN,NPC,WB_OUT);
input clk;
input RN;
//input EN;
integer k;
wire  EX_MEM_COND ;

reg 
BR_EN;

//I_FETCH STAGE
reg[31:0] 
IF_ID_IR,
IF_ID_NPC;                                

//I_DECODE STAGE
reg[31:0] 
ID_EX_A,
ID_EX_B,
ID_EX_RD,
ID_EX_IMMEDIATE,
ID_EX_IR,ID_EX_NPC;      

//EXECUTION STAGE
reg[31:0] 
EX_MEM_ALUOUT,
EX_MEM_B,EX_MEM_IR;                        

parameter 
ADD=3'd0,
SUB=3'd1,
AND=3'd2,
OR=3'd3,
XOR=3'd4,
SLT=3'd5,

ADDI=3'd0,
SUBI=3'd1,
ANDI=3'd2,
ORI=3'd3,
XORI=3'd4,

LW=3'd0,
SW=3'd1,

BEQ=3'd0,
BNE=3'd1,

SLL=3'd0,
SRL=3'd1;


parameter 
AR_TYPE=7'd0,
M_TYPE=7'd1,
BR_TYPE=7'd2,
SH_TYPE=7'd3;


//MEMORY STAGE
reg[31:0] 
MEM_WB_IR,
MEM_WB_ALUOUT,
MEM_WB_LDM;                      


output reg [31:0]WB_OUT,NPC;

//REG FILE
reg [31:0]REG[0:31];                                               
//64*32 IMEM
reg [31:0]MEM[0:63];                                             
//64*32 DMEM
reg [31:0]DM[0:31];   


//assign EX_MEM_COND = (EX_MEM_IR[6:0]==BR_TYPE) ? 1'b1 : 1'b0;
                     //1'b1 ? (ID_EX_A!=ID_EX_RD) : 1'b0;

always @(posedge clk or posedge RN) begin
    if(RN) begin
    NPC<= 32'd0;
    //EX_MEM_COND <=1'd0;
    BR_EN<= 1'd0; 
    REG[0] <= 32'h00000000;
    REG[1] <= 32'd1;
    REG[2] <= 32'd2;
    REG[3] <= 32'd3;
    REG[4] <= 32'd4;
    REG[5] <= 32'd5;
    REG[6] <= 32'd6;
    REG[7] = 32'd7;
	REG[8] = 32'd8;
	REG[9] = 32'd9;
	REG[10] = 32'd10;
	REG[11] = 32'd11;
	REG[12] = 32'd12;
	REG[13] = 32'd13;
	REG[14] = 32'd14;
	REG[15] = 32'd15;
	REG[16] = 32'd16;
	REG[17] = 32'd17;
    end
    //else if(EX_MEM_COND)
    //NPC <= EX_MEM_ALUOUT;

    //else if (EX_MEM_COND)begin
    //NPC = EX_MEM_COND ? EX_MEM_ALUOUT : NPC +32'd1;
    //NPC <= EX_MEM_ALUOUT;
    //EX_MEM_COND = BR_EN;
    //NPC = BR_EN ? EX_MEM_ALUOUT : NPC +32'd1;
    //BR_EN = 1'd0;
    //EX_MEM_COND <= 1'd0;
    //end
    else begin
    NPC <= BR_EN ? EX_MEM_ALUOUT : NPC +32'd1;
    BR_EN <= 1'd0;
    //NPC <= NPC +32'd1;
    //EX_MEM_COND <=1'd0;
    IF_ID_IR <=MEM[NPC];
    IF_ID_NPC <=NPC+32'd1;
    end
end

always @(posedge RN) begin
    //NPC<= 32'd0;
MEM[0] <= 32'h02208300;         // add r6,r1,r2.(i1)
MEM[1] <= 32'h02209380;         //sub r7,r1,r2.(i2)
MEM[2] <= 32'h0230a400;         //and r8,r1,r3.(i3)
MEM[3] <= 32'h02513480;         //or r9,r2,r5.(i4)
MEM[4] <= 32'h0240c500;         //xor r10,r1,r4.(i5)
MEM[5] <= 32'h02415580;         //slt r11,r2,r4.(i6)
MEM[6] <= 32'h00520600;         //addi r12,r4,5.(i7)
MEM[7] <= 32'h00209181;         //sw r3,r1,2.(i8)
MEM[8] <= 32'h00208681;         //lw r13,r1,2.(i9)
MEM[9]  <= 32'h00f00002;         //beq r0,r0,15.(i10)
MEM[25] <= 32'h00210700;         //add r14,r2,r2.(i11)
MEM[27] <= 32'h01409002;         //bne r0,r1,20.(i12)
MEM[49] <= 32'h00520601;         //addi r12,r4,5.(i13)
MEM[50] <= 32'h00208783;         //sll r15,r1,r2(2).(i14)
MEM[51] <= 32'h00271803;         //srl r16,r14,r2(2).(i15) 

//for(k=0;k<=31;k++)
//REG[k]<=k;
/*REG[0] <= 32'h00000000;
REG[1] <= 32'd1;
REG[2] <= 32'd2;
REG[3] <= 32'd3;
REG[4] <= 32'd4;
REG[5] <= 32'd5;
REG[6] <= 32'd6;
REG[7] = 32'd7;
REG[6] = 32'd6;
REG[7] = 32'd7;
REG[8] = 32'd8;
REG[9] = 32'd9;
REG[10] = 32'd10;
REG[11] = 32'd11;
REG[12] = 32'd12;
REG[13] = 32'd13;
REG[14] = 32'd14;
REG[15] = 32'd15;
REG[16] = 32'd16;
REG[17] = 32'd17;*/
/*end
else begin
    if(EX_MEM_COND==1 && EX_MEM_IR[6:0]==BR_TYPE) begin
    NPC=EX_MEM_ALUOUT;
    IF_ID=MEM[NPC];
    end

    else begin
    NPC<=NPC+32'd1;
    IF_ID<=MEM[NPC];
    IF_ID_NPC<=NPC+32'd1;
    end
end*/
end
//I_FECT STAGE

/*always @(posedge clk) begin

//NPC <= rst ? 32'd0 : NPC+32'd1;

if(EX_MEM_COND==1 && EX_MEM_IR[6:0]==BR_TYPE) begin
NPC=EX_MEM_ALUOUT;
IF_ID_IR=MEM[NPC];
end

else begin
NPC<=NPC+32'd1;
IF_ID_IR<=MEM[NPC];
IF_ID_NPC<=NPC+32'd1;
end
end*/


//FETCH STAGE END

//I_DECODE STAGE 
always @(posedge clk) begin

ID_EX_A <= REG[IF_ID_IR[19:15]];
ID_EX_B <= REG[IF_ID_IR[24:20]];
ID_EX_RD <= REG[IF_ID_IR[11:7]];
ID_EX_IR <= IF_ID_IR;
ID_EX_IMMEDIATE <= {{20{IF_ID_IR[31]}},IF_ID_IR[31:20]};
ID_EX_NPC<=IF_ID_NPC;
end
//DECODE STAGE END

/*always@(posedge clk) begin
if(ID_EX_IR[6:0]== BR_TYPE)
EX_MEM_COND <= EN;
else
EX_MEM_COND <= !EN;
end*/


//EXECUTION STAGE

always@(posedge clk) begin

EX_MEM_IR <=  ID_EX_IR;
//EX_MEM_COND <= (ID_EX_IR[6:0] == BR_TYPE) ? 1'd1 :1'd0;


case(ID_EX_IR[6:0])

AR_TYPE:begin
    if(ID_EX_IR[31:25]== 7'd1)begin
    case(ID_EX_IR[14:12])

    ADD:EX_MEM_ALUOUT <= ID_EX_A + ID_EX_B;
    SUB:EX_MEM_ALUOUT <= ID_EX_A - ID_EX_B;
    AND:EX_MEM_ALUOUT <= ID_EX_A & ID_EX_B;
    OR :EX_MEM_ALUOUT <= ID_EX_A | ID_EX_B;
    XOR:EX_MEM_ALUOUT <= ID_EX_A ^ ID_EX_B;
    SLT:EX_MEM_ALUOUT <= (ID_EX_A < ID_EX_B) ? 32'd1 : 32'd0;

    endcase
    end
    
    else begin
        case(ID_EX_IR[14:12])
        ADDI:EX_MEM_ALUOUT <= ID_EX_A + ID_EX_IMMEDIATE;
        SUBI:EX_MEM_ALUOUT <= ID_EX_A - ID_EX_IMMEDIATE;
        ANDI:EX_MEM_ALUOUT <= ID_EX_A & ID_EX_B;
        ORI:EX_MEM_ALUOUT  <= ID_EX_A | ID_EX_B;
        XORI:EX_MEM_ALUOUT <= ID_EX_A ^ ID_EX_B;
        endcase
    end

end

M_TYPE:begin
    case(ID_EX_IR[14:12])
    LW  :EX_MEM_ALUOUT <= ID_EX_A + ID_EX_IMMEDIATE;
    SW  :EX_MEM_ALUOUT <= ID_EX_IR[24:20] + ID_EX_IR[19:15];
    endcase
end

BR_TYPE:begin
    case(ID_EX_IR[14:12])
    BEQ:begin 
    EX_MEM_ALUOUT <= ID_EX_NPC+ID_EX_IMMEDIATE;
    BR_EN <= 1'd1 ? (ID_EX_IR[19:15] == ID_EX_IR[11:7]) : 1'd0;
    //BR_PC = EX_MEM_COND ? EX_MEM_ALUOUT : 1'd0; 
end
BNE:begin 
    EX_MEM_ALUOUT <= ID_EX_NPC+ID_EX_IMMEDIATE;
    BR_EN <= (ID_EX_IR[19:15] != ID_EX_IR[11:7]) ? 1'd1 : 1'd0;
end
endcase
end

SH_TYPE:begin
case(ID_EX_IR[14:12])
SLL:EX_MEM_ALUOUT <= ID_EX_A << ID_EX_B;
SRL:EX_MEM_ALUOUT <= ID_EX_A >> ID_EX_B;
endcase
end

endcase
end


//EXECUTION STAGE END
		
//MEMORY STAGE
always@(posedge clk) begin

MEM_WB_IR <= EX_MEM_IR;

case(EX_MEM_IR[6:0])

AR_TYPE:MEM_WB_ALUOUT <=  EX_MEM_ALUOUT;
SH_TYPE:MEM_WB_ALUOUT <=  EX_MEM_ALUOUT;

M_TYPE:begin
case(EX_MEM_IR[14:12])
LW:MEM_WB_LDM <= DM[EX_MEM_ALUOUT];
SW:DM[EX_MEM_ALUOUT]<=REG[EX_MEM_IR[11:7]];
endcase
end

endcase
end

// MEMORY STAGE END


//WRITE BACK STAGE
always@(posedge clk) begin

case(MEM_WB_IR[6:0])

AR_TYPE:begin 
WB_OUT<=MEM_WB_ALUOUT;
REG[MEM_WB_IR[11:7]]<=MEM_WB_ALUOUT;
end

SH_TYPE:begin
WB_OUT<=MEM_WB_ALUOUT;
REG[MEM_WB_IR[11:7]]<=MEM_WB_ALUOUT;
end

M_TYPE:begin
case(MEM_WB_IR[14:12])
LW:begin
WB_OUT<=MEM_WB_LDM;
REG[MEM_WB_IR[11:7]]<=MEM_WB_LDM;
end
endcase
end



endcase
end
//WRITE BACK STAGE END

endmodule

rv32i/iiitb_rv32i_tb.v
`timescale 100us/100us

module iiitb_rv32i_tb;

reg clk,RN;
wire [31:0]WB_OUT,NPC;

iiitb_rv32i rv32(clk,RN,NPC,WB_OUT);


always #3 clk=!clk;

initial begin 
RN  = 1'b1;
clk = 1'b0;

$dumpfile ("iiitb_rv32i.vcd"); //by default vcd
$dumpvars (0, iiitb_rv32i_tb);
  
  #5 RN = 1'b0;
  
  #300 $finish;

end
endmodule

rv32i/iiitb_rv32i.vcd
$date
	Mon Mar  4 19:49:35 2024
$end
$version
	Icarus Verilog
$end
$timescale
	100us
$end
$scope module iiitb_rv32i_tb $end
$var wire 32 ! WB_OUT [31:0] $end
$var wire 32 " NPC [31:0] $end
$var reg 1 # RN $end
$var reg 1 $ clk $end
$scope module rv32 $end
$var wire 1 # RN $end
$var wire 1 $ clk $end
$var reg 1 % BR_EN $end
$var reg 32 & EX_MEM_ALUOUT [31:0] $end
$var reg 32 ' EX_MEM_IR [31:0] $end
$var reg 32 ( ID_EX_A [31:0] $end
$var reg 32 ) ID_EX_B [31:0] $end
$var reg 32 * ID_EX_IMMEDIATE [31:0] $end
$var reg 32 + ID_EX_IR [31:0] $end
$var reg 32 , ID_EX_NPC [31:0] $end
$var reg 32 - ID_EX_RD [31:0] $end
$var reg 32 . IF_ID_IR [31:0] $end
$var reg 32 / IF_ID_NPC [31:0] $end
$var reg 32 0 MEM_WB_ALUOUT [31:0] $end
$var reg 32 1 MEM_WB_IR [31:0] $end
$var reg 32 2 MEM_WB_LDM [31:0] $end
$var reg 32 3 NPC [31:0] $end
$var reg 32 4 WB_OUT [31:0] $end
$upscope $end
$upscope $end
$enddefinitions $end
#0
$dumpvars
bx 4
b0 3
bx 2
bx 1
bx 0
bx /
bx .
bx -
bx ,
bx +
bx *
bx )
bx (
bx '
bx &
0%
0$
1#
b0 "
bx !
$end
#3
1$
#5
0#
#6
0$
#9
b1 /
b10001000001000001100000000 .
b1 "
b1 3
1$
#12
0$
#15
b1 ,
b100010 *
b10001000001000001100000000 +
b110 -
b10 )
b1 (
b10 /
b10001000001001001110000000 .
b10 "
b10 3
1$
#18
0$
#21
b11 &
b10001000001000001100000000 '
b10 ,
b10001000001001001110000000 +
b111 -
b11 /
b10001100001010010000000000 .
b11 "
b11 3
1$
#24
0$
#27
b11 ,
b100011 *
b10001100001010010000000000 +
b1000 -
b11 )
b11111111111111111111111111111111 &
b10001000001001001110000000 '
b11 0
b10001000001000001100000000 1
b100 /
b10010100010011010010000000 .
b100 "
b100 3
1$
#30
0$
#33
b11 !
b11 4
b11111111111111111111111111111111 0
b10001000001001001110000000 1
b1 &
b10001100001010010000000000 '
b100 ,
b100101 *
b10010100010011010010000000 +
b1001 -
b101 )
b10 (
b101 /
b10010000001100010100000000 .
b101 "
b101 3
1$
#36
0$
#39
b101 ,
b100100 *
b10010000001100010100000000 +
b1010 -
b100 )
b1 (
b111 &
b10010100010011010010000000 '
b1 0
b10001100001010010000000000 1
b11111111111111111111111111111111 !
b11111111111111111111111111111111 4
b110 /
b10010000010101010110000000 .
b110 "
b110 3
1$
#42
0$
#45
b1 !
b1 4
b111 0
b10010100010011010010000000 1
b101 &
b10010000001100010100000000 '
b110 ,
b10010000010101010110000000 +
b1011 -
b10 (
b111 /
b10100100000011000000000 .
b111 "
b111 3
1$
#48
0$
#51
b111 ,
b101 *
b10100100000011000000000 +
b1100 -
b101 )
b100 (
b1 &
b10010000010101010110000000 '
b101 0
b10010000001100010100000000 1
b111 !
b111 4
b1000 /
b1000001001000110000001 .
b1000 "
b1000 3
1$
#54
0$
#57
b101 !
b101 4
b1 0
b10010000010101010110000000 1
b1001 &
b10100100000011000000000 '
b1000 ,
b10 *
b1000001001000110000001 +
b11 -
b10 )
b1 (
b1001 /
b1000001000011010000001 .
b1001 "
b1001 3
1$
#60
0$
#63
b1001 ,
b1000001000011010000001 +
b1101 -
b11 &
b1000001001000110000001 '
b1001 0
b10100100000011000000000 1
b1 !
b1 4
b1010 /
b111100000000000000000010 .
b1010 "
b1010 3
1$
#66
0$
#69
b1001 !
b1001 4
b1000001001000110000001 1
b1000001000011010000001 '
b1010 ,
b1111 *
b111100000000000000000010 +
b0 -
b1111 )
b0 (
b1011 /
b1000010000011100000000 .
b1011 "
b1011 3
1$
#72
0$
#75
b1011 ,
b10 *
b1000010000011100000000 +
b1110 -
b10 )
b10 (
1%
b11001 &
b111100000000000000000010 '
b11 2
b1000001000011010000001 1
b1100 /
b1010000001001000000000010 .
b1100 "
b1100 3
1$
#78
0$
#81
b11 !
b11 4
b111100000000000000000010 1
b100 &
b1000010000011100000000 '
b1100 ,
b10100 *
b1010000001001000000000010 +
b0 -
bx )
b1 (
b1101 /
b10100100000011000000001 .
0%
b11001 "
b11001 3
1$
#84
0$
#87
b1101 ,
b101 *
b10100100000011000000001 +
b1001 -
b101 )
b100 (
1%
b100000 &
b1010000001001000000000010 '
b100 0
b1000010000011100000000 1
b11010 /
bx .
b11010 "
b11010 3
1$
#90
0$
#93
b100 !
b100 4
b1010000001001000000000010 1
b1001 &
b10100100000011000000001 '
b11010 ,
bx *
bx +
bx -
bx )
bx (
b11011 /
0%
b100000 "
b100000 3
1$
#96
0$
#99
b11011 ,
bx '
bx 2
b10100100000011000000001 1
b100001 /
b100001 "
b100001 3
1$
#102
0$
#105
bx !
bx 4
bx 1
b100001 ,
b100010 /
b100010 "
b100010 3
1$
#108
0$
#111
b100010 ,
b100011 /
b100011 "
b100011 3
1$
#114
0$
#117
b100011 ,
b100100 /
b100100 "
b100100 3
1$
#120
0$
#123
b100100 ,
b100101 /
b100101 "
b100101 3
1$
#126
0$
#129
b100101 ,
b100110 /
b100110 "
b100110 3
1$
#132
0$
#135
b100110 ,
b100111 /
b100111 "
b100111 3
1$
#138
0$
#141
b100111 ,
b101000 /
b101000 "
b101000 3
1$
#144
0$
#147
b101000 ,
b101001 /
b101001 "
b101001 3
1$
#150
0$
#153
b101001 ,
b101010 /
b101010 "
b101010 3
1$
#156
0$
#159
b101010 ,
b101011 /
b101011 "
b101011 3
1$
#162
0$
#165
b101011 ,
b101100 /
b101100 "
b101100 3
1$
#168
0$
#171
b101100 ,
b101101 /
b101101 "
b101101 3
1$
#174
0$
#177
b101101 ,
b101110 /
b101110 "
b101110 3
1$
#180
0$
#183
b101110 ,
b101111 /
b101111 "
b101111 3
1$
#186
0$
#189
b101111 ,
b110000 /
b110000 "
b110000 3
1$
#192
0$
#195
b110000 ,
b110001 /
b110001 "
b110001 3
1$
#198
0$
#201
b110001 ,
b110010 /
b110010 "
b110010 3
1$
#204
0$
#207
b110010 ,
b110011 /
b110011 "
b110011 3
1$
#210
0$
#213
b110011 ,
b110100 /
b110100 "
b110100 3
1$
#216
0$
#219
b110100 ,
b110101 /
b110101 "
b110101 3
1$
#222
0$
#225
b110101 ,
b110110 /
b110110 "
b110110 3
1$
#228
0$
#231
b110110 ,
b110111 /
b110111 "
b110111 3
1$
#234
0$
#237
b110111 ,
b111000 /
b111000 "
b111000 3
1$
#240
0$
#243
b111000 ,
b111001 /
b111001 "
b111001 3
1$
#246
0$
#249
b111001 ,
b111010 /
b111010 "
b111010 3
1$
#252
0$
#255
b111010 ,
b111011 /
b111011 "
b111011 3
1$
#258
0$
#261
b111011 ,
b111100 /
b111100 "
b111100 3
1$
#264
0$
#267
b111100 ,
b111101 /
b111101 "
b111101 3
1$
#270
0$
#273
b111101 ,
b111110 /
b111110 "
b111110 3
1$
#276
0$
#279
b111110 ,
b111111 /
b111111 "
b111111 3
1$
#282
0$
#285
b111111 ,
b1000000 /
b1000000 "
b1000000 3
1$
#288
0$
#291
b1000000 ,
b1000001 /
b1000001 "
b1000001 3
1$
#294
0$
#297
b1000001 ,
b1000010 /
b1000010 "
b1000010 3
1$
#300
0$
#303
b1000010 ,
b1000011 /
b1000011 "
b1000011 3
1$
